bbrf/__init__.py
bbrf/bbrf.py
bbrf/bbrf_api.py
src/__init__.py
src/bbrf.py
src/bbrf_api.py
src/test/__init__.py
src/test/bbrf_test.py
bbrf-1.3.2.dist-info/LICENSE
bbrf-1.3.2.dist-info/METADATA
bbrf-1.3.2.dist-info/WHEEL
bbrf-1.3.2.dist-info/entry_points.txt
bbrf-1.3.2.dist-info/top_level.txt
bbrf-1.3.2.dist-info/RECORD
