Metadata-Version: 2.1
Name: bbrf
Version: 1.3.2
Summary: The client component of the Bug Bounty Reconnaissance Framework (BBRF)
Home-page: https://github.com/honoki/bbrf-client
Author: @honoki
Author-email: pieter@honoki.net
License: UNKNOWN
Platform: UNKNOWN
Classifier: Programming Language :: Python :: 3
Classifier: License :: OSI Approved :: MIT License
Classifier: Operating System :: OS Independent
Requires-Python: >=3.5
Requires-Dist: docopt
Requires-Dist: requests
Requires-Dist: slack-sdk
